ix_notifiers/__init__.py
ix_notifiers/constants.py
ix_notifiers/core.py
ix_notifiers/gotify_notifier.py
ix_notifiers/notifier.py
ix_notifiers/null_notifier.py
ix_notifiers/py.typed
ix_notifiers-1.0.10.dist-info/METADATA
ix_notifiers-1.0.10.dist-info/WHEEL
ix_notifiers-1.0.10.dist-info/licenses/LICENSE
ix_notifiers-1.0.10.dist-info/RECORD
