Metadata-Version: 2.4
Name: ix-notifiers
Version: 1.0.10
Summary: A python library for notifiers
License: MIT License
License-File: LICENSE
Author: Alex Thomae
Author-email: notifiers@egos.tech
Requires-Python: >=3.12
Classifier: Intended Audience :: Developers
Classifier: Natural Language :: English
Classifier: Operating System :: OS Independent
Classifier: Programming Language :: Python
Classifier: Programming Language :: Python :: 3
Classifier: Programming Language :: Python :: 3.12
Classifier: Programming Language :: Python :: 3.13
Classifier: Programming Language :: Python :: 3.14
Classifier: Programming Language :: Python :: Implementation :: PyPy
Classifier: Topic :: Software Development :: Libraries
Requires-Dist: egos-helpers (==1.2.3)
Requires-Dist: requests (==2.32.5)
Project-URL: Homepage, https://gitlab.com/egos-tech/notifiers
Project-URL: Source, https://gitlab.com/egos-tech/notifiers
